.gitignore
.travis.yml
LICENSE
README.md
check_performance.py
requirements-test.txt
requirements.txt
setup.py
docs/edinet.md
docs/images/bs.png
tests/__init__.py
tests/utils.py
tests/edinet/__init__.py
tests/edinet/test_api.py
tests/edinet/client/__init__.py
tests/edinet/client/test_document.py
tests/edinet/client/test_document_list_client.py
tests/edinet/data/test_example_1.pdf
tests/edinet/data/xbrl2018.xbrl
tests/edinet/data/xbrl2019.xbrl
tests/edinet/model/__init__.py
tests/edinet/model/test_document.py
tests/edinet/reader/__init__.py
tests/edinet/reader/test_base_parser.py
tests/edinet/reader/test_directory.py
tests/edinet/reader/test_reader.py
tests/edinet/reader/aspects/__init__.py
tests/edinet/reader/aspects/test_business.py
tests/edinet/reader/aspects/test_company.py
tests/edinet/reader/aspects/test_finance.py
tests/edinet/reader/aspects/test_information.py
tests/edinet/reader/aspects/test_metadata.py
xbrr/__init__.py
xbrr.egg-info/PKG-INFO
xbrr.egg-info/SOURCES.txt
xbrr.egg-info/dependency_links.txt
xbrr.egg-info/requires.txt
xbrr.egg-info/top_level.txt
xbrr/base/__init__.py
xbrr/base/reader/__init__.py
xbrr/base/reader/base_element.py
xbrr/base/reader/base_element_schema.py
xbrr/base/reader/base_element_value.py
xbrr/base/reader/base_parser.py
xbrr/base/reader/base_reader.py
xbrr/edinet/__init__.py
xbrr/edinet/facade.py
xbrr/edinet/client/__init__.py
xbrr/edinet/client/base_client.py
xbrr/edinet/client/document_client.py
xbrr/edinet/client/document_list_client.py
xbrr/edinet/models/__init__.py
xbrr/edinet/models/document.py
xbrr/edinet/models/documents.py
xbrr/edinet/models/error_response.py
xbrr/edinet/models/metadata.py
xbrr/edinet/reader/__init__.py
xbrr/edinet/reader/directory.py
xbrr/edinet/reader/element.py
xbrr/edinet/reader/element_schema.py
xbrr/edinet/reader/element_value.py
xbrr/edinet/reader/reader.py
xbrr/edinet/reader/taxonomy.py
xbrr/edinet/reader/aspects/__init__.py
xbrr/edinet/reader/aspects/business.py
xbrr/edinet/reader/aspects/company.py
xbrr/edinet/reader/aspects/finance.py
xbrr/edinet/reader/aspects/information.py
xbrr/edinet/reader/aspects/metadata.py