Metadata-Version: 2.1
Name: xbrr
Version: 0.2.2
Summary: eXtensible Business Report Reader.
Home-page: https://github.com/chakki-works/xbrr
Author: icoxfog417
Author-email: icoxfog417@yahoo.co.jp
License: MIT
Keywords: XBRL,EDINET,API
Platform: UNKNOWN
